<stack>
  <description brief="haikalpribadi-ros-pkg">haikalpribadi-ros-pkg</description>
  <author>Maintained by Haikal Pribadi (haikal.pribadi@gmail.com)</author>
  <license>BSD</license>  
  <review status="unreviewed" notes=""/>
  <url>http://ros.org/wiki/haikalpribadi-ros-pkg</url>
  <depend stack="common_msgs" /> <!-- sensor_msgs -->
  <depend stack="image_common" /> <!-- image_transport -->
  <depend stack="kinect" /> <!-- kinect_aux -->
  <depend stack="openni_kinect" /> <!-- openni_tracker -->
  <depend stack="rharmony" /> <!-- pocketsphinx -->
  <depend stack="ros" />
  <depend stack="ros_comm" /> <!-- std_msgs, roscpp -->
  <depend stack="vision_opencv" /> <!-- opencv2, cv_bridge -->

</stack>
